django_chatter/__init__.py
django_chatter/admin.py
django_chatter/apps.py
django_chatter/consumers.py
django_chatter/models.py
django_chatter/routing.py
django_chatter/urls.py
django_chatter/utils.py
django_chatter/views.py
django_chatter/migrations/0001_initial.py
django_chatter/migrations/0002_auto_20190524_2308.py
django_chatter/migrations/0003_auto_20190524_2315.py
django_chatter/migrations/__init__.py
django_chatter/static/css/base.css
django_chatter/static/css/chat-window.css
django_chatter/static/css/chatroom-list.css
django_chatter/static/css/index.css
django_chatter/static/img/left-arrow.svg
django_chatter/static/img/send-button.svg
django_chatter/static/js/alertSocket.js
django_chatter/static/js/chatSocket.js
django_chatter/static/js/chatWindow.js
django_chatter/static/js/dateFormatter.js
django_chatter/static/js/fetchMessages.js
django_chatter/static/js/searchUser.js
django_chatter/static/js/websocketHelpers.js
django_chatter/templates/django_chatter/base.html
django_chatter/templates/django_chatter/chat-window.html
django_chatter/templates/django_chatter/chatroom-list.html
django_chatter/templates/django_chatter/index.html
django_chatter/tests/__init__.py
django_chatter/tests/test_consumers.py
django_chatter/tests/test_models.py
django_chatter/tests/test_utils.py
django_chatter/tests/test_views.py
functional_tests/__init__.py
functional_tests/data_setup_for_tests.py
functional_tests/test_chat_behavior.py
tenants/__init__.py
tenants/admin.py
tenants/apps.py
tenants/models.py
tenants/tests.py
tenants/views.py
tenants/migrations/0001_initial.py
tenants/migrations/0002_auto_20190521_0816.py
tenants/migrations/__init__.py
django_chatter-1.0.7.dist-info/LICENSE
django_chatter-1.0.7.dist-info/METADATA
django_chatter-1.0.7.dist-info/WHEEL
django_chatter-1.0.7.dist-info/top_level.txt
django_chatter-1.0.7.dist-info/RECORD
