Metadata-Version: 2.1
Name: django-chatter
Version: 1.0.7
Summary: A WebSocket-based Chat app for Django developers.
Home-page: https://www.github.com/dibs-devs/chatter
Author: Ahmed Ishtiaque, Dibs
Author-email: ahmedishti27@gmail.com
License: MIT License
Platform: UNKNOWN
Classifier: Environment :: Web Environment
Classifier: Framework :: Django
Classifier: Framework :: Django :: 2.0
Classifier: Intended Audience :: Developers
Classifier: License :: OSI Approved :: MIT License
Classifier: Operating System :: OS Independent
Classifier: Programming Language :: Python
Classifier: Programming Language :: Python :: 3.5
Classifier: Programming Language :: Python :: 3.6
Classifier: Topic :: Internet :: WWW/HTTP
Classifier: Topic :: Internet :: WWW/HTTP :: Dynamic Content
